pyPSCF/BackTrajHysplit.py
pyPSCF/__init__.py
pyPSCF/pyPSCF.py
pyPSCF-0.1.3.dist-info/DESCRIPTION.rst
pyPSCF-0.1.3.dist-info/METADATA
pyPSCF-0.1.3.dist-info/RECORD
pyPSCF-0.1.3.dist-info/WHEEL
pyPSCF-0.1.3.dist-info/metadata.json
pyPSCF-0.1.3.dist-info/top_level.txt
