Metadata-Version: 2.0
Name: pyPSCF
Version: 0.1.3
Summary: A Hysplit backtraj and PSCF tool for atmospheric science
Home-page: https://gricad-gitlab.univ-grenoble-alpes.fr/webersa/pyPSCF
Author: Samuël Weber
Author-email: samuel.weber@univ-grenoble-alpes.fr
License: UNKNOWN
Project-URL: Documentation, https://pypscf.readthedocs.io/en/latest/
Project-URL: Source, https://gricad-gitlab.univ-grenoble-alpes.fr/webersa/pyPSCF
Platform: UNKNOWN
Classifier: Programming Language :: Python
Classifier: Development Status :: 1 - Planning
Classifier: License :: OSI Approved
Classifier: Natural Language :: English
Classifier: Operating System :: OS Independent
Classifier: Programming Language :: Python :: 3
Classifier: Topic :: Scientific/Engineering :: Atmospheric Science
Requires-Python: >=3
Provides-Extra: plot
Requires-Dist: matplotlib
Requires-Dist: numpy
Requires-Dist: pandas
Requires-Dist: scipy
Provides-Extra: plot
Requires-Dist: cartopy; extra == 'plot'
